reaktiv/__init__.py
reaktiv/_debug.py
reaktiv/context.py
reaktiv/effect.py
reaktiv/graph.py
reaktiv/linked.py
reaktiv/protocols.py
reaktiv/resource.py
reaktiv/scheduler.py
reaktiv/signal.py
reaktiv/thread_safety.py
reaktiv/types.py
reaktiv/utils.py
reaktiv-0.21.0.dist-info/METADATA
reaktiv-0.21.0.dist-info/WHEEL
reaktiv-0.21.0.dist-info/top_level.txt
reaktiv-0.21.0.dist-info/RECORD
