Metadata-Version: 2.4
Name: reaktiv
Version: 0.21.0
Summary: Signals for Python - inspired by Angular Signals / SolidJS. Reactive Declarative State Management Library for Python - automatic dependency tracking and reactive updates for your application state.
Author-email: Tuan Anh Bui <mail@bui.app>
License: MIT
Project-URL: Homepage, https://github.com/buiapp/reaktiv
Classifier: License :: OSI Approved :: MIT License
Classifier: Programming Language :: Python :: 3
Classifier: Programming Language :: Python :: 3.9
Classifier: Programming Language :: Python :: 3.10
Classifier: Programming Language :: Python :: 3.11
Classifier: Programming Language :: Python :: 3.12
Requires-Python: >=3.9
